atcp.py
atcp-1.0.0.dist-info/METADATA
atcp-1.0.0.dist-info/WHEEL
atcp-1.0.0.dist-info/top_level.txt
atcp-1.0.0.dist-info/RECORD
