Metadata-Version: 2.2
Name: atcp
Version: 1.0.0
Summary: An ATCP Protocol
License: MIT License
Project-URL: Homepage, https://github.com/wer310/atcp
Project-URL: Issues, https://github.com/wer310/atcp/issues
Classifier: Programming Language :: Python :: 3
Classifier: Operating System :: OS Independent
Requires-Python: >=3.8
